vcert/__init__.py
vcert/common.py
vcert/connection_cloud.py
vcert/connection_fake.py
vcert/connection_tpp.py
vcert/connection_tpp_abstract.py
vcert/connection_tpp_token.py
vcert/errors.py
vcert/http_status.py
vcert/logger.py
vcert/pem.py
vcert/ssh_utils.py
vcert/tpp_utils.py
vcert/vaas_utils.py
vcert/parser/__init__.py
vcert/parser/json_parser.py
vcert/parser/utils.py
vcert/parser/yaml_parser.py
vcert/policy/__init__.py
vcert/policy/pm_cloud.py
vcert/policy/pm_tpp.py
vcert/policy/policy_spec.py
vcert-0.18.1.dist-info/licenses/LICENSE
vcert-0.18.1.dist-info/METADATA
vcert-0.18.1.dist-info/WHEEL
vcert-0.18.1.dist-info/top_level.txt
vcert-0.18.1.dist-info/RECORD
