Metadata-Version: 2.4
Name: vcert
Version: 0.18.1
Summary: Python client library for Venafi Trust Protection Platform and Venafi Cloud.
Home-page: https://github.com/Venafi/vcert-python
Author: Venafi, Inc.
Author-email: opensource@venafi.com
License: ASL
Classifier: Programming Language :: Python :: 3.9
Classifier: Programming Language :: Python :: 3.10
Classifier: Operating System :: OS Independent
Classifier: License :: OSI Approved :: Apache Software License
License-File: LICENSE
Requires-Dist: requests==2.32.4
Requires-Dist: python-dateutil==2.8.2
Requires-Dist: six==1.17.0
Requires-Dist: cryptography==45.0.7
Requires-Dist: ruamel.yaml==0.18.13
Requires-Dist: pynacl==1.5.0
Dynamic: author
Dynamic: author-email
Dynamic: classifier
Dynamic: description
Dynamic: description-content-type
Dynamic: home-page
Dynamic: license
Dynamic: license-file
Dynamic: requires-dist
Dynamic: summary
